kolibri_desktop_auth_plugin/__init__.py
kolibri_desktop_auth_plugin/kolibri_plugin.py
kolibri_desktop_auth_plugin/migrations/0001_initial.py
kolibri_desktop_auth_plugin/migrations/0002_desktop_user_to_os_user.py
kolibri_desktop_auth_plugin/migrations/__init__.py
kolibri_desktop_auth_plugin-1.0.0.dist-info/METADATA
kolibri_desktop_auth_plugin-1.0.0.dist-info/WHEEL
kolibri_desktop_auth_plugin-1.0.0.dist-info/entry_points.txt
kolibri_desktop_auth_plugin-1.0.0.dist-info/top_level.txt
kolibri_desktop_auth_plugin-1.0.0.dist-info/RECORD
