Metadata-Version: 2.1
Name: kolibri_desktop_auth_plugin
Version: 1.0.0
Summary: Kolibri plugin for desktop authentication
Home-page: https://github.com/endlessm/kolibri-desktop-auth-plugin
Author: EndlessOS
Author-email: danigm@endless.org
License: MIT
Keywords: kolibri
Classifier: Development Status :: 2 - Pre-Alpha
Classifier: Intended Audience :: Developers
Classifier: License :: OSI Approved :: MIT License
Classifier: Natural Language :: English
Classifier: Programming Language :: Python :: 3
Classifier: Programming Language :: Python :: 3.3
Classifier: Programming Language :: Python :: 3.4
Classifier: Programming Language :: Python :: 3.5
Classifier: Programming Language :: Python :: 3.6
Classifier: Programming Language :: Python :: 3.7
Classifier: Programming Language :: Python :: 3.8
Classifier: Programming Language :: Python :: Implementation :: PyPy
